osbm/VERSION
osbm/__init__.py
osbm/imaging.py
osbm/utils.py
tests/__init__.py
tests/test_imaging.py
osbm-0.1.0.dist-info/LICENSE
osbm-0.1.0.dist-info/METADATA
osbm-0.1.0.dist-info/WHEEL
osbm-0.1.0.dist-info/top_level.txt
osbm-0.1.0.dist-info/RECORD
